arcane/date.py
arcane_date-0.1.4.dist-info/METADATA
arcane_date-0.1.4.dist-info/WHEEL
arcane_date-0.1.4.dist-info/RECORD
